sortseqsoftware/__init__.py
sortseqsoftware/learn_model.py
sortseqsoftware/nsbestimator.py
sortseqsoftware/errfromtags.py
sortseqsoftware/select_window.py
sortseqsoftware/simulate_selection.py
sortseqsoftware/stepper.py
sortseqsoftware/predictiveinfo.py
sortseqsoftware/compare_predictive_info.py
sortseqsoftware/draw.py
sortseqsoftware/simulate_evaluate.py
sortseqsoftware/plot_converge.py
sortseqsoftware/simulate_sort.py
sortseqsoftware/EstimateMutualInfoforMImax.py
sortseqsoftware/compute_MI_RNA.py
sortseqsoftware/pairwise_mutrate.py
sortseqsoftware/simulate_library.py
sortseqsoftware/optimize_rna_seq.py
sortseqsoftware/compare_predictive_information.py
sortseqsoftware/find_total_seq_dep_info.py
sortseqsoftware/profile_freqs.py
sortseqsoftware/EstimateMutualInfo.py
sortseqsoftware/profile_mutrate.py
sortseqsoftware/simulate_expression.py
sortseqsoftware/Sublib.py
sortseqsoftware/MIhigherdim.py
sortseqsoftware/logratio.py
sortseqsoftware/profile_info.py
sortseqsoftware/profile_counts.py
sortseqsoftware/simulate_RNAseq_lib.py
sortseqsoftware/profile_enrichment.py
sortseqsoftware/profile_info_test.py
sortseqsoftware/gatherseqs.py
sortseqsoftware/utils.py
sortseqsoftware/Models.py
sortseqsoftware/fromto_mutrate.py
sortseqsoftware/simulate_sublibrary.py
sortseq/__init__.py
sortseq/learn_model.py
sortseq/_metadata.py
sortseq/nsbestimator.py
sortseq/errfromtags.py
sortseq/select_window.py
sortseq/simulate_selection.py
sortseq/stepper.py
sortseq/predictiveinfo.py
sortseq/compare_predictive_info.py
sortseq/draw.py
sortseq/simulate_evaluate.py
sortseq/plot_converge.py
sortseq/simulate_sort.py
sortseq/EstimateMutualInfoforMImax.py
sortseq/compute_MI_RNA.py
sortseq/pairwise_mutrate.py
sortseq/simulate_library.py
sortseq/optimize_rna_seq.py
sortseq/preprocess.py
sortseq/compare_predictive_information.py
sortseq/find_total_seq_dep_info.py
sortseq/profile_freqs.py
sortseq/EstimateMutualInfo.py
sortseq-0.0.1.dist-info/WHEEL
sortseq-0.0.1.dist-info/top_level.txt
sortseq-0.0.1.dist-info/METADATA
sortseq-0.0.1.dist-info/RECORD
sortseq-0.0.1.dist-info/DESCRIPTION.rst
sortseq-0.0.1.dist-info/metadata.json
