Metadata-Version: 2.0
Name: sortseq
Version: 0.0.1
Summary: Tools for analysis of Sort-Seq experiments.
Home-page: UNKNOWN
Author: UNKNOWN
Author-email: UNKNOWN
License: UNKNOWN
Download-URL: https://github.com/jbkinney/15_sortseqtools/tarball/0.1
Platform: Linux (and maybe also Mac OS X).
Requires-Dist: biopython (>=1.6)
Requires-Dist: scipy (>=0.13)
Requires-Dist: numpy (>=1.8)
Requires-Dist: pymc (>=2.3.4)
Requires-Dist: scikit-learn (>=0.15.2)
Requires-Dist: statsmodels (>=0.5.0)
Requires-Dist: mpmath (>=0.19)
Requires-Dist: pandas (>=0.16.2)
